{"cameraMode":{"drawMode":0,"name":"Shaded","section":"Shading Mode"},"sceneLighting":false,"audioPlay":false,"sceneViewState":{"showFog":true,"showMaterialUpdate":false,"showSkybox":false,"showFlares":true,"showImageEffects":true,"showParticleSystems":true},"in2DMode":false,"pivot":{"x":7.085107803344727,"y":6.279963493347168,"z":-4.922046661376953},"rotation":{"x":0.05582863464951515,"y":-0.9352335333824158,"z":0.1685786098241806,"w":0.30681395530700686},"size":8.988195419311524,"orthographic":false}